tests/__init__.py
tests/test_typed_llm.py
typed_llm/__init__.py
typed_llm/tools/__init__.py
typed_llm/tools/typed_llm.py
typed_llm/tools/utils.py
typed_llm/yamls/typed_llm.yaml
promptflow_typed_llm-0.0.9.dist-info/LICENSE
promptflow_typed_llm-0.0.9.dist-info/METADATA
promptflow_typed_llm-0.0.9.dist-info/WHEEL
promptflow_typed_llm-0.0.9.dist-info/entry_points.txt
promptflow_typed_llm-0.0.9.dist-info/top_level.txt
promptflow_typed_llm-0.0.9.dist-info/RECORD
